Workbook
Name ak: 'Summary ELN '!$A$1:$A$1634

Sheet Summary
C3: Product | D3: Available licenses | E3: 2025 usage | F3: 2026 (Jan&Feb) usage | G3: %usage 2025 | H3: % usage 2026 | I3: Cost of license
C4: ELN | D4: 1953 | E4: 1773 | F4: 1632 | G4: =E4/D4 -> 0.9078341 | H4: =F4/D4 -> 0.83563748 | I4: 502869
C5: PLP | D5: 490 | E5: 278 | F5: 185 | G5: =E5/D5 -> 0.56734694 | H5: =F5/D5 -> 0.37755102 | I5: 264592
C7: Total | I7: =SUM(I4:I5) -> 767461

Sheet Summary ELN 
A1: Username | B1: Jan | C1: Feb | E1: Cum'26
A2: SUPERUSER | B2: Y | C2: Y | D2: Y | E2: =IF(COUNTIF(B2:D2,"Y")>0,1,0) -> 1
A3: ADMIN_ELLEN | B3: Y | C3: Y | D3: Y | E3: =IF(COUNTIF(B3:D3,"Y")>0,1,0) -> 1
A4: SYNCSERVICE | B4: Y | C4: Y | D4: Y | E4: =IF(COUNTIF(B4:D4,"Y")>0,1,0) -> 1
A5: _PP_SERVICEACCOUNT | B5: Y | C5: Y | D5: Y | E5: =IF(COUNTIF(B5:D5,"Y")>0,1,0) -> 1
A6: TERESA.LOUGHBROUGH_ADMIN | B6: Y | C6: Y | D6: N | E6: =IF(COUNTIF(B6:D6,"Y")>0,1,0) -> 1
A7: SANGAMESH.SAJJAN_ADMIN | B7: Y | C7: Y | D7: N | E7: =IF(COUNTIF(B7:D7,"Y")>0,1,0) -> 1
A8: GERARD.VOLANTE_ADMIN | B8: Y | C8: Y | D8: N | E8: =IF(COUNTIF(B8:D8,"Y")>0,1,0) -> 1
A9: POORNA.TAGIRISA_ADMIN | B9: Y | C9: Y | D9: N | E9: =IF(COUNTIF(B9:D9,"Y")>0,1,0) -> 1
A10: FARHA.SULTHANA2_ADMIN | B10: Y | C10: Y | D10: N | E10: =IF(COUNTIF(B10:D10,"Y")>0,1,0) -> 1
A11: VEERAPRATHAPREDD.SI_ADMIN | B11: Y | C11: Y | D11: N | E11: =IF(COUNTIF(B11:D11,"Y")>0,1,0) -> 1
A12: RAHUL.RAHUL_ADMIN | B12: Y | C12: Y | D12: N | E12: =IF(COUNTIF(B12:D12,"Y")>0,1,0) -> 1
A13: SANGAMESH.SAJJAN2_ADMIN | B13: Y | C13: Y | D13: N | E13: =IF(COUNTIF(B13:D13,"Y")>0,1,0) -> 1
... A1633: MADHAVI.KOCHAREKAR | B1633: Y | C1633: N | D1633: N | E1633: =IF(COUNTIF(B1633:D1633,"Y")>0,1,0) -> 1
A1634: ANTHONY.MCKEE | B1634: N | C1634: N | E1634: =IF(COUNTIF(B1634:D1634,"Y")>0,1,0) -> 0
A1635: GEORGE.MULKERRIN | B1635: N | C1635: N | D1635: Y | E1635: =IF(COUNTIF(B1635:D1635,"Y")>0,1,0) -> 1
A1636: CLARE.A.JONES | B1636: N | C1636: N | D1636: Y | E1636: =IF(COUNTIF(B1636:D1636,"Y")>0,1,0) -> 1
A1637: VADIVEL.G | B1637: N | C1637: N | D1637: Y | E1637: =IF(COUNTIF(B1637:D1637,"Y")>0,1,0) -> 1
A1638: JULIET.SAMUEL | B1638: N | C1638: N | D1638: Y | E1638: =IF(COUNTIF(B1638:D1638,"Y")>0,1,0) -> 1
A1639: SUJATHA.JAYARAMAN | B1639: N | C1639: N | D1639: Y | E1639: =IF(COUNTIF(B1639:D1639,"Y")>0,1,0) -> 1
A1640: LOKESH.BASAVARAJU | B1640: N | C1640: N | D1640: Y | E1640: =IF(COUNTIF(B1640:D1640,"Y")>0,1,0) -> 1
A1641: DEEPAK.MHASAVADE | B1641: N | C1641: N | D1641: Y | E1641: =IF(COUNTIF(B1641:D1641,"Y")>0,1,0) -> 1
A1642: AMANDA.LANE | B1642: N | C1642: N | D1642: Y | E1642: =IF(COUNTIF(B1642:D1642,"Y")>0,1,0) -> 1
A1643: HASIBA.PEHRATOVIC | B1643: N | C1643: N | D1643: Y | E1643: =IF(COUNTIF(B1643:D1643,"Y")>0,1,0) -> 1
A1644: MARISKA.DOTSCH | B1644: N | C1644: N | D1644: Y | E1644: =IF(COUNTIF(B1644:D1644,"Y")>0,1,0) -> 1
A1645: LEO-VAN.BUREN | B1645: N | C1645: N | D1645: Y | E1645: =IF(COUNTIF(B1645:D1645,"Y")>0,1,0) -> 1
A1646: WENDY.BLOM | B1646: N | C1646: N | D1646: Y | E1646: =IF(COUNTIF(B1646:D1646,"Y")>0,1,0) -> 1
... A1824: PH-NGOC.THAI | B1824: N | C1824: N | D1824: Y | E1824: =IF(COUNTIF(B1824:D1824,"Y")>0,1,0) -> 1
A1826: Total | B1826: =COUNTIF(B2:B1824,"Y") -> 1522 | C1826: =COUNTIF(C2:C1824,"Y") -> 1559 | D1826: =COUNTIF(D2:D1824,"Y") -> 1665 | E1826: =SUM(E2:E1824) -> 1822

Sheet Sheet1
A1: Username | B1: Jan | C1: Feb | E1: Cum'26
A2: SUPERUSER | B2: Y | C2: Y | E2: 1
A3: ADMIN_ELLEN | B3: Y | C3: Y | E3: 1
A4: SYNCSERVICE | B4: Y | C4: Y | E4: 1
A5: _PP_SERVICEACCOUNT | B5: Y | C5: Y | E5: 1
A6: TERESA.LOUGHBROUGH_ADMIN | B6: Y | C6: Y | E6: 1
A7: SANGAMESH.SAJJAN_ADMIN | B7: Y | C7: Y | E7: 1
A8: GERARD.VOLANTE_ADMIN | B8: Y | C8: Y | E8: 1
A9: POORNA.TAGIRISA_ADMIN | B9: Y | C9: Y | E9: 1
A10: FARHA.SULTHANA2_ADMIN | B10: Y | C10: Y | E10: 1
A11: VEERAPRATHAPREDD.SI_ADMIN | B11: Y | C11: Y | E11: 1
A12: RAHUL.RAHUL_ADMIN | B12: Y | C12: Y | E12: 1
A13: SANGAMESH.SAJJAN2_ADMIN | B13: Y | C13: Y | E13: 1
... A1633: MADHAVI.KOCHAREKAR | B1633: Y | C1633: N | E1633: 1
A1635: Total | B1635: 1522 | C1635: 1559 | E1635: 1632
A1637: Check | B1637: 1522 | C1637: 1559 | E1637: 1632

Sheet Summary PLP
B1: Jan'26 | G1: Feb'26 | L1: Mar'26 | R1: Cum 2026 | S1: Cum 2025
A2: User Id | B2: RDPLP | C2: SCINET | D2: FLEX | E2: ELN | F2: Total | G2: RDPLP | H2: SCINET | I2: FLEX | J2: ELN | K2: Total | L2: RDPLP | M2: SCINET | N2: FLEX | O2: ELN | P2: Total | R2: Total | S2: Total | Z2: adam.newbould
A3: amautomation.nonsap2 | B3: =IF(ISERROR(VLOOKUP(A3,RDPLP!A3:A28,1,0)),"N","Y") -> Y | C3: =IF(ISERROR(VLOOKUP(A3,'SCINET-PLP'!A:A,1,0)),"N","Y") -> N | D3: =IF(ISERROR(VLOOKUP(A3,FLEXPLP!A:A,1,0)),"N","Y") -> N | E3: =IF(ISERROR(VLOOKUP(A3,'ELN PLP'!A:A,1,0)),"N","Y") -> Y | F3: =IF(COUNTIF(B3:E3,"Y")>0,1,0) -> 1 | G3: =IF(ISERROR(VLOOKUP(A3,RDPLP!D:D,1,0)),"N","Y") -> Y | H3: =IF(ISERROR(VLOOKUP(A3,'SCINET-PLP'!D:D,1,0)),"N","Y") -> N | I3: =IF(ISERROR(VLOOKUP(A3,FLEXPLP!D:D,1,0)),"N","Y") -> N | J3: =IF(ISERROR(VLOOKUP(A3,'ELN PLP'!D:D,1,0)),"N","Y") -> Y | K3: =IF(COUNTIF(G3:J3,"Y")>0,1,0) -> 1 | L3: =IF(ISERROR(VLOOKUP(A3,RDPLP!G:G,1,0)),"N","Y") -> Y | M3: =IF(ISERROR(VLOOKUP(A3,'SCINET-PLP'!G:G,1,0)),"N","Y") -> N | N3: =IF(ISERROR(VLOOKUP(A3,FLEXPLP!G:G,1,0)),"N","Y") -> N | O3: =IF(ISERROR(VLOOKUP(A3,'ELN PLP'!G:G,1,0)),"N","Y") -> Y | P3: =IF(COUNTIF(L3:O3,"Y")>0,1,0) -> 1 | R3: =IF(K3+F3>0,1,0) -> 1 | S3: =IF(ISERROR(VLOOKUP(A3,U:U,1,0)),0,1) -> 0 | Z3: adrian.williams
A4: helena.johnston | B4: =IF(ISERROR(VLOOKUP(A4,RDPLP!A4:A29,1,0)),"N","Y") -> Y | C4: =IF(ISERROR(VLOOKUP(A4,'SCINET-PLP'!A:A,1,0)),"N","Y") -> N | D4: =IF(ISERROR(VLOOKUP(A4,FLEXPLP!A:A,1,0)),"N","Y") -> Y | E4: =IF(ISERROR(VLOOKUP(A4,'ELN PLP'!A:A,1,0)),"N","Y") -> N | F4: =IF(COUNTIF(B4:E4,"Y")>0,1,0) -> 1 | G4: =IF(ISERROR(VLOOKUP(A4,RDPLP!D:D,1,0)),"N","Y") -> Y | H4: =IF(ISERROR(VLOOKUP(A4,'SCINET-PLP'!D:D,1,0)),"N","Y") -> N | I4: =IF(ISERROR(VLOOKUP(A4,FLEXPLP!D:D,1,0)),"N","Y") -> Y | J4: =IF(ISERROR(VLOOKUP(A4,'ELN PLP'!D:D,1,0)),"N","Y") -> N | K4: =IF(COUNTIF(G4:J4,"Y")>0,1,0) -> 1 | L4: =IF(ISERROR(VLOOKUP(A4,RDPLP!G:G,1,0)),"N","Y") -> Y | M4: =IF(ISERROR(VLOOKUP(A4,'SCINET-PLP'!G:G,1,0)),"N","Y") -> Y | N4: =IF(ISERROR(VLOOKUP(A4,FLEXPLP!G:G,1,0)),"N","Y") -> N | O4: =IF(ISERROR(VLOOKUP(A4,'ELN PLP'!G:G,1,0)),"N","Y") -> N | P4: =IF(COUNTIF(L4:O4,"Y")>0,1,0) -> 1 | R4: =IF(K4+F4>0,1,0) -> 1 | S4: =IF(ISERROR(VLOOKUP(A4,U:U,1,0)),0,1) -> 0 | Z4: andrew.a.barnes
A5: kareena.bains | B5: =IF(ISERROR(VLOOKUP(A5,RDPLP!A5:A30,1,0)),"N","Y") -> Y | C5: =IF(ISERROR(VLOOKUP(A5,'SCINET-PLP'!A:A,1,0)),"N","Y") -> N | D5: =IF(ISERROR(VLOOKUP(A5,FLEXPLP!A:A,1,0)),"N","Y") -> Y | E5: =IF(ISERROR(VLOOKUP(A5,'ELN PLP'!A:A,1,0)),"N","Y") -> N | F5: =IF(COUNTIF(B5:E5,"Y")>0,1,0) -> 1 | G5: =IF(ISERROR(VLOOKUP(A5,RDPLP!D:D,1,0)),"N","Y") -> Y | H5: =IF(ISERROR(VLOOKUP(A5,'SCINET-PLP'!D:D,1,0)),"N","Y") -> N | I5: =IF(ISERROR(VLOOKUP(A5,FLEXPLP!D:D,1,0)),"N","Y") -> Y | J5: =IF(ISERROR(VLOOKUP(A5,'ELN PLP'!D:D,1,0)),"N","Y") -> N | K5: =IF(COUNTIF(G5:J5,"Y")>0,1,0) -> 1 | L5: =IF(ISERROR(VLOOKUP(A5,RDPLP!G:G,1,0)),"N","Y") -> Y | M5: =IF(ISERROR(VLOOKUP(A5,'SCINET-PLP'!G:G,1,0)),"N","Y") -> N | N5: =IF(ISERROR(VLOOKUP(A5,FLEXPLP!G:G,1,0)),"N","Y") -> Y | O5: =IF(ISERROR(VLOOKUP(A5,'ELN PLP'!G:G,1,0)),"N","Y") -> N | P5: =IF(COUNTIF(L5:O5,"Y")>0,1,0) -> 1 | R5: =IF(K5+F5>0,1,0) -> 1 | S5: =IF(ISERROR(VLOOKUP(A5,U:U,1,0)),0,1) -> 0 | Z5: andrew.mitchell
A6: emma.elliott | B6: =IF(ISERROR(VLOOKUP(A6,RDPLP!A6:A31,1,0)),"N","Y") -> Y | C6: =IF(ISERROR(VLOOKUP(A6,'SCINET-PLP'!A:A,1,0)),"N","Y") -> N | D6: =IF(ISERROR(VLOOKUP(A6,FLEXPLP!A:A,1,0)),"N","Y") -> Y | E6: =IF(ISERROR(VLOOKUP(A6,'ELN PLP'!A:A,1,0)),"N","Y") -> N | F6: =IF(COUNTIF(B6:E6,"Y")>0,1,0) -> 1 | G6: =IF(ISERROR(VLOOKUP(A6,RDPLP!D:D,1,0)),"N","Y") -> Y | H6: =IF(ISERROR(VLOOKUP(A6,'SCINET-PLP'!D:D,1,0)),"N","Y") -> N | I6: =IF(ISERROR(VLOOKUP(A6,FLEXPLP!D:D,1,0)),"N","Y") -> Y | J6: =IF(ISERROR(VLOOKUP(A6,'ELN PLP'!D:D,1,0)),"N","Y") -> N | K6: =IF(COUNTIF(G6:J6,"Y")>0,1,0) -> 1 | L6: =IF(ISERROR(VLOOKUP(A6,RDPLP!G:G,1,0)),"N","Y") -> Y | M6: =IF(ISERROR(VLOOKUP(A6,'SCINET-PLP'!G:G,1,0)),"N","Y") -> N | N6: =IF(ISERROR(VLOOKUP(A6,FLEXPLP!G:G,1,0)),"N","Y") -> Y | O6: =IF(ISERROR(VLOOKUP(A6,'ELN PLP'!G:G,1,0)),"N","Y") -> N | P6: =IF(COUNTIF(L6:O6,"Y")>0,1,0) -> 1 | R6: =IF(K6+F6>0,1,0) -> 1 | S6: =IF(ISERROR(VLOOKUP(A6,U:U,1,0)),0,1) -> 0 | Z6: andrew.ng
A7: andrew.ng | B7: =IF(ISERROR(VLOOKUP(A7,RDPLP!A7:A32,1,0)),"N","Y") -> Y | C7: =IF(ISERROR(VLOOKUP(A7,'SCINET-PLP'!A:A,1,0)),"N","Y") -> N | D7: =IF(ISERROR(VLOOKUP(A7,FLEXPLP!A:A,1,0)),"N","Y") -> Y | E7: =IF(ISERROR(VLOOKUP(A7,'ELN PLP'!A:A,1,0)),"N","Y") -> N | F7: =IF(COUNTIF(B7:E7,"Y")>0,1,0) -> 1 | G7: =IF(ISERROR(VLOOKUP(A7,RDPLP!D:D,1,0)),"N","Y") -> Y | H7: =IF(ISERROR(VLOOKUP(A7,'SCINET-PLP'!D:D,1,0)),"N","Y") -> N | I7: =IF(ISERROR(VLOOKUP(A7,FLEXPLP!D:D,1,0)),"N","Y") -> N | J7: =IF(ISERROR(VLOOKUP(A7,'ELN PLP'!D:D,1,0)),"N","Y") -> N | K7: =IF(COUNTIF(G7:J7,"Y")>0,1,0) -> 1 | L7: =IF(ISERROR(VLOOKUP(A7,RDPLP!G:G,1,0)),"N","Y") -> Y | M7: =IF(ISERROR(VLOOKUP(A7,'SCINET-PLP'!G:G,1,0)),"N","Y") -> N | N7: =IF(ISERROR(VLOOKUP(A7,FLEXPLP!G:G,1,0)),"N","Y") -> Y | O7: =IF(ISERROR(VLOOKUP(A7,'ELN PLP'!G:G,1,0)),"N","Y") -> N | P7: =IF(COUNTIF(L7:O7,"Y")>0,1,0) -> 1 | R7: =IF(K7+F7>0,1,0) -> 1 | S7: =IF(ISERROR(VLOOKUP(A7,U:U,1,0)),0,1) -> 0 | Z7: andrew.p.parker
A8: arun.khuntia | B8: =IF(ISERROR(VLOOKUP(A8,RDPLP!A8:A33,1,0)),"N","Y") -> Y | C8: =IF(ISERROR(VLOOKUP(A8,'SCINET-PLP'!A:A,1,0)),"N","Y") -> Y | D8: =IF(ISERROR(VLOOKUP(A8,FLEXPLP!A:A,1,0)),"N","Y") -> Y | E8: =IF(ISERROR(VLOOKUP(A8,'ELN PLP'!A:A,1,0)),"N","Y") -> Y | F8: =IF(COUNTIF(B8:E8,"Y")>0,1,0) -> 1 | G8: =IF(ISERROR(VLOOKUP(A8,RDPLP!D:D,1,0)),"N","Y") -> Y | H8: =IF(ISERROR(VLOOKUP(A8,'SCINET-PLP'!D:D,1,0)),"N","Y") -> Y | I8: =IF(ISERROR(VLOOKUP(A8,FLEXPLP!D:D,1,0)),"N","Y") -> Y | J8: =IF(ISERROR(VLOOKUP(A8,'ELN PLP'!D:D,1,0)),"N","Y") -> Y | K8: =IF(COUNTIF(G8:J8,"Y")>0,1,0) -> 1 | L8: =IF(ISERROR(VLOOKUP(A8,RDPLP!G:G,1,0)),"N","Y") -> Y | M8: =IF(ISERROR(VLOOKUP(A8,'SCINET-PLP'!G:G,1,0)),"N","Y") -> Y | N8: =IF(ISERROR(VLOOKUP(A8,FLEXPLP!G:G,1,0)),"N","Y") -> Y | O8: =IF(ISERROR(VLOOKUP(A8,'ELN PLP'!G:G,1,0)),"N","Y") -> Y | P8: =IF(COUNTIF(L8:O8,"Y")>0,1,0) -> 1 | R8: =IF(K8+F8>0,1,0) -> 1 | S8: =IF(ISERROR(VLOOKUP(A8,U:U,1,0)),0,1) -> 0 | Z8: aniket.chitre
A9: adam.newbould | B9: =IF(ISERROR(VLOOKUP(A9,RDPLP!A9:A34,1,0)),"N","Y") -> Y | C9: =IF(ISERROR(VLOOKUP(A9,'SCINET-PLP'!A:A,1,0)),"N","Y") -> N | D9: =IF(ISERROR(VLOOKUP(A9,FLEXPLP!A:A,1,0)),"N","Y") -> Y | E9: =IF(ISERROR(VLOOKUP(A9,'ELN PLP'!A:A,1,0)),"N","Y") -> N | F9: =IF(COUNTIF(B9:E9,"Y")>0,1,0) -> 1 | G9: =IF(ISERROR(VLOOKUP(A9,RDPLP!D:D,1,0)),"N","Y") -> Y | H9: =IF(ISERROR(VLOOKUP(A9,'SCINET-PLP'!D:D,1,0)),"N","Y") -> N | I9: =IF(ISERROR(VLOOKUP(A9,FLEXPLP!D:D,1,0)),"N","Y") -> Y | J9: =IF(ISERROR(VLOOKUP(A9,'ELN PLP'!D:D,1,0)),"N","Y") -> N | K9: =IF(COUNTIF(G9:J9,"Y")>0,1,0) -> 1 | L9: =IF(ISERROR(VLOOKUP(A9,RDPLP!G:G,1,0)),"N","Y") -> Y | M9: =IF(ISERROR(VLOOKUP(A9,'SCINET-PLP'!G:G,1,0)),"N","Y") -> N | N9: =IF(ISERROR(VLOOKUP(A9,FLEXPLP!G:G,1,0)),"N","Y") -> Y | O9: =IF(ISERROR(VLOOKUP(A9,'ELN PLP'!G:G,1,0)),"N","Y") -> N | P9: =IF(COUNTIF(L9:O9,"Y")>0,1,0) -> 1 | R9: =IF(K9+F9>0,1,0) -> 1 | S9: =IF(ISERROR(VLOOKUP(A9,U:U,1,0)),0,1) -> 0 | Z9: archita.jain
A10: noah.phipps | B10: =IF(ISERROR(VLOOKUP(A10,RDPLP!A10:A35,1,0)),"N","Y") -> Y | C10: =IF(ISERROR(VLOOKUP(A10,'SCINET-PLP'!A:A,1,0)),"N","Y") -> N | D10: =IF(ISERROR(VLOOKUP(A10,FLEXPLP!A:A,1,0)),"N","Y") -> Y | E10: =IF(ISERROR(VLOOKUP(A10,'ELN PLP'!A:A,1,0)),"N","Y") -> N | F10: =IF(COUNTIF(B10:E10,"Y")>0,1,0) -> 1 | G10: =IF(ISERROR(VLOOKUP(A10,RDPLP!D:D,1,0)),"N","Y") -> Y | H10: =IF(ISERROR(VLOOKUP(A10,'SCINET-PLP'!D:D,1,0)),"N","Y") -> N | I10: =IF(ISERROR(VLOOKUP(A10,FLEXPLP!D:D,1,0)),"N","Y") -> N | J10: =IF(ISERROR(VLOOKUP(A10,'ELN PLP'!D:D,1,0)),"N","Y") -> N | K10: =IF(COUNTIF(G10:J10,"Y")>0,1,0) -> 1 | L10: =IF(ISERROR(VLOOKUP(A10,RDPLP!G:G,1,0)),"N","Y") -> N | M10: =IF(ISERROR(VLOOKUP(A10,'SCINET-PLP'!G:G,1,0)),"N","Y") -> N | N10: =IF(ISERROR(VLOOKUP(A10,FLEXPLP!G:G,1,0)),"N","Y") -> Y | O10: =IF(ISERROR(VLOOKUP(A10,'ELN PLP'!G:G,1,0)),"N","Y") -> N | P10: =IF(COUNTIF(L10:O10,"Y")>0,1,0) -> 1 | R10: =IF(K10+F10>0,1,0) -> 1 | S10: =IF(ISERROR(VLOOKUP(A10,U:U,1,0)),0,1) -> 0 | Z10: arun.khuntia
A11: rahida.islam | B11: =IF(ISERROR(VLOOKUP(A11,RDPLP!A11:A36,1,0)),"N","Y") -> Y | C11: =IF(ISERROR(VLOOKUP(A11,'SCINET-PLP'!A:A,1,0)),"N","Y") -> N | D11: =IF(ISERROR(VLOOKUP(A11,FLEXPLP!A:A,1,0)),"N","Y") -> Y | E11: =IF(ISERROR(VLOOKUP(A11,'ELN PLP'!A:A,1,0)),"N","Y") -> N | F11: =IF(COUNTIF(B11:E11,"Y")>0,1,0) -> 1 | G11: =IF(ISERROR(VLOOKUP(A11,RDPLP!D:D,1,0)),"N","Y") -> Y | H11: =IF(ISERROR(VLOOKUP(A11,'SCINET-PLP'!D:D,1,0)),"N","Y") -> N | I11: =IF(ISERROR(VLOOKUP(A11,FLEXPLP!D:D,1,0)),"N","Y") -> Y | J11: =IF(ISERROR(VLOOKUP(A11,'ELN PLP'!D:D,1,0)),"N","Y") -> N | K11: =IF(COUNTIF(G11:J11,"Y")>0,1,0) -> 1 | L11: =IF(ISERROR(VLOOKUP(A11,RDPLP!G:G,1,0)),"N","Y") -> N | M11: =IF(ISERROR(VLOOKUP(A11,'SCINET-PLP'!G:G,1,0)),"N","Y") -> N | N11: =IF(ISERROR(VLOOKUP(A11,FLEXPLP!G:G,1,0)),"N","Y") -> N | O11: =IF(ISERROR(VLOOKUP(A11,'ELN PLP'!G:G,1,0)),"N","Y") -> N | P11: =IF(COUNTIF(L11:O11,"Y")>0,1,0) -> 0 | R11: =IF(K11+F11>0,1,0) -> 1 | S11: =IF(ISERROR(VLOOKUP(A11,U:U,1,0)),0,1) -> 0 | Z11: ashelyn.kyne
A12: andrew.a.barnes | B12: =IF(ISERROR(VLOOKUP(A12,RDPLP!A12:A37,1,0)),"N","Y") -> Y | C12: =IF(ISERROR(VLOOKUP(A12,'SCINET-PLP'!A:A,1,0)),"N","Y") -> N | D12: =IF(ISERROR(VLOOKUP(A12,FLEXPLP!A:A,1,0)),"N","Y") -> Y | E12: =IF(ISERROR(VLOOKUP(A12,'ELN PLP'!A:A,1,0)),"N","Y") -> N | F12: =IF(COUNTIF(B12:E12,"Y")>0,1,0) -> 1 | G12: =IF(ISERROR(VLOOKUP(A12,RDPLP!D:D,1,0)),"N","Y") -> Y | H12: =IF(ISERROR(VLOOKUP(A12,'SCINET-PLP'!D:D,1,0)),"N","Y") -> N | I12: =IF(ISERROR(VLOOKUP(A12,FLEXPLP!D:D,1,0)),"N","Y") -> Y | J12: =IF(ISERROR(VLOOKUP(A12,'ELN PLP'!D:D,1,0)),"N","Y") -> N | K12: =IF(COUNTIF(G12:J12,"Y")>0,1,0) -> 1 | L12: =IF(ISERROR(VLOOKUP(A12,RDPLP!G:G,1,0)),"N","Y") -> Y | M12: =IF(ISERROR(VLOOKUP(A12,'SCINET-PLP'!G:G,1,0)),"N","Y") -> N | N12: =IF(ISERROR(VLOOKUP(A12,FLEXPLP!G:G,1,0)),"N","Y") -> Y | O12: =IF(ISERROR(VLOOKUP(A12,'ELN PLP'!G:G,1,0)),"N","Y") -> N | P12: =IF(COUNTIF(L12:O12,"Y")>0,1,0) -> 1 | R12: =IF(K12+F12>0,1,0) -> 1 | S12: =IF(ISERROR(VLOOKUP(A12,U:U,1,0)),0,1) -> 0 | Z12: beatrice.fekete
A13: bhakti.varadkar | B13: =IF(ISERROR(VLOOKUP(A13,RDPLP!A13:A38,1,0)),"N","Y") -> Y | C13: =IF(ISERROR(VLOOKUP(A13,'SCINET-PLP'!A:A,1,0)),"N","Y") -> N | D13: =IF(ISERROR(VLOOKUP(A13,FLEXPLP!A:A,1,0)),"N","Y") -> N | E13: =IF(ISERROR(VLOOKUP(A13,'ELN PLP'!A:A,1,0)),"N","Y") -> N | F13: =IF(COUNTIF(B13:E13,"Y")>0,1,0) -> 1 | G13: =IF(ISERROR(VLOOKUP(A13,RDPLP!D:D,1,0)),"N","Y") -> Y | H13: =IF(ISERROR(VLOOKUP(A13,'SCINET-PLP'!D:D,1,0)),"N","Y") -> N | I13: =IF(ISERROR(VLOOKUP(A13,FLEXPLP!D:D,1,0)),"N","Y") -> Y | J13: =IF(ISERROR(VLOOKUP(A13,'ELN PLP'!D:D,1,0)),"N","Y") -> N | K13: =IF(COUNTIF(G13:J13,"Y")>0,1,0) -> 1 | L13: =IF(ISERROR(VLOOKUP(A13,RDPLP!G:G,1,0)),"N","Y") -> N | M13: =IF(ISERROR(VLOOKUP(A13,'SCINET-PLP'!G:G,1,0)),"N","Y") -> N | N13: =IF(ISERROR(VLOOKUP(A13,FLEXPLP!G:G,1,0)),"N","Y") -> N | O13: =IF(ISERROR(VLOOKUP(A13,'ELN PLP'!G:G,1,0)),"N","Y") -> N | P13: =IF(COUNTIF(L13:O13,"Y")>0,1,0) -> 0 | R13: =IF(K13+F13>0,1,0) -> 1 | S13: =IF(ISERROR(VLOOKUP(A13,U:U,1,0)),0,1) -> 0 | Z13: bhakti.varadkar
A14: samuel.sandiford | B14: =IF(ISERROR(VLOOKUP(A14,RDPLP!A14:A39,1,0)),"N","Y") -> Y | C14: =IF(ISERROR(VLOOKUP(A14,'SCINET-PLP'!A:A,1,0)),"N","Y") -> N | D14: =IF(ISERROR(VLOOKUP(A14,FLEXPLP!A:A,1,0)),"N","Y") -> Y | E14: =IF(ISERROR(VLOOKUP(A14,'ELN PLP'!A:A,1,0)),"N","Y") -> N | F14: =IF(COUNTIF(B14:E14,"Y")>0,1,0) -> 1 | G14: =IF(ISERROR(VLOOKUP(A14,RDPLP!D:D,1,0)),"N","Y") -> Y | H14: =IF(ISERROR(VLOOKUP(A14,'SCINET-PLP'!D:D,1,0)),"N","Y") -> N | I14: =IF(ISERROR(VLOOKUP(A14,FLEXPLP!D:D,1,0)),"N","Y") -> Y | J14: =IF(ISERROR(VLOOKUP(A14,'ELN PLP'!D:D,1,0)),"N","Y") -> N | K14: =IF(COUNTIF(G14:J14,"Y")>0,1,0) -> 1 | L14: =IF(ISERROR(VLOOKUP(A14,RDPLP!G:G,1,0)),"N","Y") -> Y | M14: =IF(ISERROR(VLOOKUP(A14,'SCINET-PLP'!G:G,1,0)),"N","Y") -> Y | N14: =IF(ISERROR(VLOOKUP(A14,FLEXPLP!G:G,1,0)),"N","Y") -> Y | O14: =IF(ISERROR(VLOOKUP(A14,'ELN PLP'!G:G,1,0)),"N","Y") -> N | P14: =IF(COUNTIF(L14:O14,"Y")>0,1,0) -> 1 | R14: =IF(K14+F14>0,1,0) -> 1 | S14: =IF(ISERROR(VLOOKUP(A14,U:U,1,0)),0,1) -> 0 | Z14: caitlin.kirwan
... A279: Hana.Kolikkal | B279: =IF(ISERROR(VLOOKUP(A279,RDPLP!A279:A304,1,0)),"N","Y") -> N | C279: =IF(ISERROR(VLOOKUP(A279,'SCINET-PLP'!A:A,1,0)),"N","Y") -> N | D279: =IF(ISERROR(VLOOKUP(A279,FLEXPLP!A:A,1,0)),"N","Y") -> N | E279: =IF(ISERROR(VLOOKUP(A279,'ELN PLP'!A:A,1,0)),"N","Y") -> N | F279: =IF(COUNTIF(B279:E279,"Y")>0,1,0) -> 0 | G279: =IF(ISERROR(VLOOKUP(A279,RDPLP!D:D,1,0)),"N","Y") -> N | H279: =IF(ISERROR(VLOOKUP(A279,'SCINET-PLP'!D:D,1,0)),"N","Y") -> N | I279: =IF(ISERROR(VLOOKUP(A279,FLEXPLP!D:D,1,0)),"N","Y") -> N | J279: =IF(ISERROR(VLOOKUP(A279,'ELN PLP'!D:D,1,0)),"N","Y") -> N | K279: =IF(COUNTIF(G279:J279,"Y")>0,1,0) -> 0 | L279: =IF(ISERROR(VLOOKUP(A279,RDPLP!G:G,1,0)),"N","Y") -> N | M279: =IF(ISERROR(VLOOKUP(A279,'SCINET-PLP'!G:G,1,0)),"N","Y") -> N | N279: =IF(ISERROR(VLOOKUP(A279,FLEXPLP!G:G,1,0)),"N","Y") -> N | O279: =IF(ISERROR(VLOOKUP(A279,'ELN PLP'!G:G,1,0)),"N","Y") -> N | P279: =IF(COUNTIF(L279:O279,"Y")>0,1,0) -> 0 | R279: =IF(K279+F279>0,1,0) -> 0 | S279: =IF(ISERROR(VLOOKUP(A279,U:U,1,0)),0,1) -> 0 | Z279: zaida.salazar
A280: Heidi.Biltcliffe-Gray | B280: =IF(ISERROR(VLOOKUP(A280,RDPLP!A280:A305,1,0)),"N","Y") -> N | C280: =IF(ISERROR(VLOOKUP(A280,'SCINET-PLP'!A:A,1,0)),"N","Y") -> N | D280: =IF(ISERROR(VLOOKUP(A280,FLEXPLP!A:A,1,0)),"N","Y") -> N | E280: =IF(ISERROR(VLOOKUP(A280,'ELN PLP'!A:A,1,0)),"N","Y") -> N | F280: =IF(COUNTIF(B280:E280,"Y")>0,1,0) -> 0 | G280: =IF(ISERROR(VLOOKUP(A280,RDPLP!D:D,1,0)),"N","Y") -> N | H280: =IF(ISERROR(VLOOKUP(A280,'SCINET-PLP'!D:D,1,0)),"N","Y") -> N | I280: =IF(ISERROR(VLOOKUP(A280,FLEXPLP!D:D,1,0)),"N","Y") -> N | J280: =IF(ISERROR(VLOOKUP(A280,'ELN PLP'!D:D,1,0)),"N","Y") -> N | K280: =IF(COUNTIF(G280:J280,"Y")>0,1,0) -> 0 | L280: =IF(ISERROR(VLOOKUP(A280,RDPLP!G:G,1,0)),"N","Y") -> N | M280: =IF(ISERROR(VLOOKUP(A280,'SCINET-PLP'!G:G,1,0)),"N","Y") -> N | N280: =IF(ISERROR(VLOOKUP(A280,FLEXPLP!G:G,1,0)),"N","Y") -> N | O280: =IF(ISERROR(VLOOKUP(A280,'ELN PLP'!G:G,1,0)),"N","Y") -> N | P280: =IF(COUNTIF(L280:O280,"Y")>0,1,0) -> 0 | R280: =IF(K280+F280>0,1,0) -> 0 | S280: =IF(ISERROR(VLOOKUP(A280,U:U,1,0)),0,1) -> 0
A281: Ian.Pye | B281: =IF(ISERROR(VLOOKUP(A281,RDPLP!A281:A306,1,0)),"N","Y") -> N | C281: =IF(ISERROR(VLOOKUP(A281,'SCINET-PLP'!A:A,1,0)),"N","Y") -> N | D281: =IF(ISERROR(VLOOKUP(A281,FLEXPLP!A:A,1,0)),"N","Y") -> N | E281: =IF(ISERROR(VLOOKUP(A281,'ELN PLP'!A:A,1,0)),"N","Y") -> N | F281: =IF(COUNTIF(B281:E281,"Y")>0,1,0) -> 0 | G281: =IF(ISERROR(VLOOKUP(A281,RDPLP!D:D,1,0)),"N","Y") -> N | H281: =IF(ISERROR(VLOOKUP(A281,'SCINET-PLP'!D:D,1,0)),"N","Y") -> N | I281: =IF(ISERROR(VLOOKUP(A281,FLEXPLP!D:D,1,0)),"N","Y") -> N | J281: =IF(ISERROR(VLOOKUP(A281,'ELN PLP'!D:D,1,0)),"N","Y") -> N | K281: =IF(COUNTIF(G281:J281,"Y")>0,1,0) -> 0 | L281: =IF(ISERROR(VLOOKUP(A281,RDPLP!G:G,1,0)),"N","Y") -> N | M281: =IF(ISERROR(VLOOKUP(A281,'SCINET-PLP'!G:G,1,0)),"N","Y") -> N | N281: =IF(ISERROR(VLOOKUP(A281,FLEXPLP!G:G,1,0)),"N","Y") -> N | O281: =IF(ISERROR(VLOOKUP(A281,'ELN PLP'!G:G,1,0)),"N","Y") -> N | P281: =IF(COUNTIF(L281:O281,"Y")>0,1,0) -> 0 | R281: =IF(K281+F281>0,1,0) -> 0 | S281: =IF(ISERROR(VLOOKUP(A281,U:U,1,0)),0,1) -> 0
A282: julie.cullen | B282: =IF(ISERROR(VLOOKUP(A282,RDPLP!A282:A307,1,0)),"N","Y") -> N | C282: =IF(ISERROR(VLOOKUP(A282,'SCINET-PLP'!A:A,1,0)),"N","Y") -> N | D282: =IF(ISERROR(VLOOKUP(A282,FLEXPLP!A:A,1,0)),"N","Y") -> N | E282: =IF(ISERROR(VLOOKUP(A282,'ELN PLP'!A:A,1,0)),"N","Y") -> N | F282: =IF(COUNTIF(B282:E282,"Y")>0,1,0) -> 0 | G282: =IF(ISERROR(VLOOKUP(A282,RDPLP!D:D,1,0)),"N","Y") -> N | H282: =IF(ISERROR(VLOOKUP(A282,'SCINET-PLP'!D:D,1,0)),"N","Y") -> N | I282: =IF(ISERROR(VLOOKUP(A282,FLEXPLP!D:D,1,0)),"N","Y") -> N | J282: =IF(ISERROR(VLOOKUP(A282,'ELN PLP'!D:D,1,0)),"N","Y") -> N | K282: =IF(COUNTIF(G282:J282,"Y")>0,1,0) -> 0 | L282: =IF(ISERROR(VLOOKUP(A282,RDPLP!G:G,1,0)),"N","Y") -> N | M282: =IF(ISERROR(VLOOKUP(A282,'SCINET-PLP'!G:G,1,0)),"N","Y") -> N | N282: =IF(ISERROR(VLOOKUP(A282,FLEXPLP!G:G,1,0)),"N","Y") -> N | O282: =IF(ISERROR(VLOOKUP(A282,'ELN PLP'!G:G,1,0)),"N","Y") -> N | P282: =IF(COUNTIF(L282:O282,"Y")>0,1,0) -> 0 | R282: =IF(K282+F282>0,1,0) -> 0 | S282: =IF(ISERROR(VLOOKUP(A282,U:U,1,0)),0,1) -> 0
A283: julie.x.bennett | B283: =IF(ISERROR(VLOOKUP(A283,RDPLP!A283:A308,1,0)),"N","Y") -> N | C283: =IF(ISERROR(VLOOKUP(A283,'SCINET-PLP'!A:A,1,0)),"N","Y") -> N | D283: =IF(ISERROR(VLOOKUP(A283,FLEXPLP!A:A,1,0)),"N","Y") -> N | E283: =IF(ISERROR(VLOOKUP(A283,'ELN PLP'!A:A,1,0)),"N","Y") -> N | F283: =IF(COUNTIF(B283:E283,"Y")>0,1,0) -> 0 | G283: =IF(ISERROR(VLOOKUP(A283,RDPLP!D:D,1,0)),"N","Y") -> N | H283: =IF(ISERROR(VLOOKUP(A283,'SCINET-PLP'!D:D,1,0)),"N","Y") -> N | I283: =IF(ISERROR(VLOOKUP(A283,FLEXPLP!D:D,1,0)),"N","Y") -> N | J283: =IF(ISERROR(VLOOKUP(A283,'ELN PLP'!D:D,1,0)),"N","Y") -> N | K283: =IF(COUNTIF(G283:J283,"Y")>0,1,0) -> 0 | L283: =IF(ISERROR(VLOOKUP(A283,RDPLP!G:G,1,0)),"N","Y") -> N | M283: =IF(ISERROR(VLOOKUP(A283,'SCINET-PLP'!G:G,1,0)),"N","Y") -> N | N283: =IF(ISERROR(VLOOKUP(A283,FLEXPLP!G:G,1,0)),"N","Y") -> N | O283: =IF(ISERROR(VLOOKUP(A283,'ELN PLP'!G:G,1,0)),"N","Y") -> N | P283: =IF(COUNTIF(L283:O283,"Y")>0,1,0) -> 0 | R283: =IF(K283+F283>0,1,0) -> 0 | S283: =IF(ISERROR(VLOOKUP(A283,U:U,1,0)),0,1) -> 0
A284: Katherine.Thompson | B284: =IF(ISERROR(VLOOKUP(A284,RDPLP!A284:A309,1,0)),"N","Y") -> N | C284: =IF(ISERROR(VLOOKUP(A284,'SCINET-PLP'!A:A,1,0)),"N","Y") -> N | D284: =IF(ISERROR(VLOOKUP(A284,FLEXPLP!A:A,1,0)),"N","Y") -> N | E284: =IF(ISERROR(VLOOKUP(A284,'ELN PLP'!A:A,1,0)),"N","Y") -> N | F284: =IF(COUNTIF(B284:E284,"Y")>0,1,0) -> 0 | G284: =IF(ISERROR(VLOOKUP(A284,RDPLP!D:D,1,0)),"N","Y") -> N | H284: =IF(ISERROR(VLOOKUP(A284,'SCINET-PLP'!D:D,1,0)),"N","Y") -> N | I284: =IF(ISERROR(VLOOKUP(A284,FLEXPLP!D:D,1,0)),"N","Y") -> N | J284: =IF(ISERROR(VLOOKUP(A284,'ELN PLP'!D:D,1,0)),"N","Y") -> N | K284: =IF(COUNTIF(G284:J284,"Y")>0,1,0) -> 0 | L284: =IF(ISERROR(VLOOKUP(A284,RDPLP!G:G,1,0)),"N","Y") -> N | M284: =IF(ISERROR(VLOOKUP(A284,'SCINET-PLP'!G:G,1,0)),"N","Y") -> N | N284: =IF(ISERROR(VLOOKUP(A284,FLEXPLP!G:G,1,0)),"N","Y") -> N | O284: =IF(ISERROR(VLOOKUP(A284,'ELN PLP'!G:G,1,0)),"N","Y") -> N | P284: =IF(COUNTIF(L284:O284,"Y")>0,1,0) -> 0 | R284: =IF(K284+F284>0,1,0) -> 0 | S284: =IF(ISERROR(VLOOKUP(A284,U:U,1,0)),0,1) -> 0
A285: kopparapu.bee | B285: =IF(ISERROR(VLOOKUP(A285,RDPLP!A285:A310,1,0)),"N","Y") -> N | C285: =IF(ISERROR(VLOOKUP(A285,'SCINET-PLP'!A:A,1,0)),"N","Y") -> N | D285: =IF(ISERROR(VLOOKUP(A285,FLEXPLP!A:A,1,0)),"N","Y") -> N | E285: =IF(ISERROR(VLOOKUP(A285,'ELN PLP'!A:A,1,0)),"N","Y") -> N | F285: =IF(COUNTIF(B285:E285,"Y")>0,1,0) -> 0 | G285: =IF(ISERROR(VLOOKUP(A285,RDPLP!D:D,1,0)),"N","Y") -> N | H285: =IF(ISERROR(VLOOKUP(A285,'SCINET-PLP'!D:D,1,0)),"N","Y") -> N | I285: =IF(ISERROR(VLOOKUP(A285,FLEXPLP!D:D,1,0)),"N","Y") -> N | J285: =IF(ISERROR(VLOOKUP(A285,'ELN PLP'!D:D,1,0)),"N","Y") -> N | K285: =IF(COUNTIF(G285:J285,"Y")>0,1,0) -> 0 | L285: =IF(ISERROR(VLOOKUP(A285,RDPLP!G:G,1,0)),"N","Y") -> N | M285: =IF(ISERROR(VLOOKUP(A285,'SCINET-PLP'!G:G,1,0)),"N","Y") -> N | N285: =IF(ISERROR(VLOOKUP(A285,FLEXPLP!G:G,1,0)),"N","Y") -> N | O285: =IF(ISERROR(VLOOKUP(A285,'ELN PLP'!G:G,1,0)),"N","Y") -> N | P285: =IF(COUNTIF(L285:O285,"Y")>0,1,0) -> 0 | R285: =IF(K285+F285>0,1,0) -> 0 | S285: =IF(ISERROR(VLOOKUP(A285,U:U,1,0)),0,1) -> 0
A286: Labman.Automation | B286: =IF(ISERROR(VLOOKUP(A286,RDPLP!A286:A311,1,0)),"N","Y") -> N | C286: =IF(ISERROR(VLOOKUP(A286,'SCINET-PLP'!A:A,1,0)),"N","Y") -> N | D286: =IF(ISERROR(VLOOKUP(A286,FLEXPLP!A:A,1,0)),"N","Y") -> N | E286: =IF(ISERROR(VLOOKUP(A286,'ELN PLP'!A:A,1,0)),"N","Y") -> N | F286: =IF(COUNTIF(B286:E286,"Y")>0,1,0) -> 0 | G286: =IF(ISERROR(VLOOKUP(A286,RDPLP!D:D,1,0)),"N","Y") -> N | H286: =IF(ISERROR(VLOOKUP(A286,'SCINET-PLP'!D:D,1,0)),"N","Y") -> N | I286: =IF(ISERROR(VLOOKUP(A286,FLEXPLP!D:D,1,0)),"N","Y") -> N | J286: =IF(ISERROR(VLOOKUP(A286,'ELN PLP'!D:D,1,0)),"N","Y") -> N | K286: =IF(COUNTIF(G286:J286,"Y")>0,1,0) -> 0 | L286: =IF(ISERROR(VLOOKUP(A286,RDPLP!G:G,1,0)),"N","Y") -> N | M286: =IF(ISERROR(VLOOKUP(A286,'SCINET-PLP'!G:G,1,0)),"N","Y") -> N | N286: =IF(ISERROR(VLOOKUP(A286,FLEXPLP!G:G,1,0)),"N","Y") -> N | O286: =IF(ISERROR(VLOOKUP(A286,'ELN PLP'!G:G,1,0)),"N","Y") -> N | P286: =IF(COUNTIF(L286:O286,"Y")>0,1,0) -> 0 | R286: =IF(K286+F286>0,1,0) -> 0 | S286: =IF(ISERROR(VLOOKUP(A286,U:U,1,0)),0,1) -> 0
A287: leanne.jenkins2 | B287: =IF(ISERROR(VLOOKUP(A287,RDPLP!A287:A312,1,0)),"N","Y") -> N | C287: =IF(ISERROR(VLOOKUP(A287,'SCINET-PLP'!A:A,1,0)),"N","Y") -> N | D287: =IF(ISERROR(VLOOKUP(A287,FLEXPLP!A:A,1,0)),"N","Y") -> N | E287: =IF(ISERROR(VLOOKUP(A287,'ELN PLP'!A:A,1,0)),"N","Y") -> N | F287: =IF(COUNTIF(B287:E287,"Y")>0,1,0) -> 0 | G287: =IF(ISERROR(VLOOKUP(A287,RDPLP!D:D,1,0)),"N","Y") -> N | H287: =IF(ISERROR(VLOOKUP(A287,'SCINET-PLP'!D:D,1,0)),"N","Y") -> N | I287: =IF(ISERROR(VLOOKUP(A287,FLEXPLP!D:D,1,0)),"N","Y") -> N | J287: =IF(ISERROR(VLOOKUP(A287,'ELN PLP'!D:D,1,0)),"N","Y") -> N | K287: =IF(COUNTIF(G287:J287,"Y")>0,1,0) -> 0 | L287: =IF(ISERROR(VLOOKUP(A287,RDPLP!G:G,1,0)),"N","Y") -> N | M287: =IF(ISERROR(VLOOKUP(A287,'SCINET-PLP'!G:G,1,0)),"N","Y") -> N | N287: =IF(ISERROR(VLOOKUP(A287,FLEXPLP!G:G,1,0)),"N","Y") -> N | O287: =IF(ISERROR(VLOOKUP(A287,'ELN PLP'!G:G,1,0)),"N","Y") -> N | P287: =IF(COUNTIF(L287:O287,"Y")>0,1,0) -> 0 | R287: =IF(K287+F287>0,1,0) -> 0 | S287: =IF(ISERROR(VLOOKUP(A287,U:U,1,0)),0,1) -> 0
A288: Luke.Langton | B288: =IF(ISERROR(VLOOKUP(A288,RDPLP!A288:A313,1,0)),"N","Y") -> N | C288: =IF(ISERROR(VLOOKUP(A288,'SCINET-PLP'!A:A,1,0)),"N","Y") -> N | D288: =IF(ISERROR(VLOOKUP(A288,FLEXPLP!A:A,1,0)),"N","Y") -> N | E288: =IF(ISERROR(VLOOKUP(A288,'ELN PLP'!A:A,1,0)),"N","Y") -> N | F288: =IF(COUNTIF(B288:E288,"Y")>0,1,0) -> 0 | G288: =IF(ISERROR(VLOOKUP(A288,RDPLP!D:D,1,0)),"N","Y") -> N | H288: =IF(ISERROR(VLOOKUP(A288,'SCINET-PLP'!D:D,1,0)),"N","Y") -> N | I288: =IF(ISERROR(VLOOKUP(A288,FLEXPLP!D:D,1,0)),"N","Y") -> N | J288: =IF(ISERROR(VLOOKUP(A288,'ELN PLP'!D:D,1,0)),"N","Y") -> N | K288: =IF(COUNTIF(G288:J288,"Y")>0,1,0) -> 0 | L288: =IF(ISERROR(VLOOKUP(A288,RDPLP!G:G,1,0)),"N","Y") -> N | M288: =IF(ISERROR(VLOOKUP(A288,'SCINET-PLP'!G:G,1,0)),"N","Y") -> N | N288: =IF(ISERROR(VLOOKUP(A288,FLEXPLP!G:G,1,0)),"N","Y") -> N | O288: =IF(ISERROR(VLOOKUP(A288,'ELN PLP'!G:G,1,0)),"N","Y") -> N | P288: =IF(COUNTIF(L288:O288,"Y")>0,1,0) -> 0 | R288: =IF(K288+F288>0,1,0) -> 0 | S288: =IF(ISERROR(VLOOKUP(A288,U:U,1,0)),0,1) -> 0
A289: Michael.cooke | B289: =IF(ISERROR(VLOOKUP(A289,RDPLP!A289:A314,1,0)),"N","Y") -> N | C289: =IF(ISERROR(VLOOKUP(A289,'SCINET-PLP'!A:A,1,0)),"N","Y") -> N | D289: =IF(ISERROR(VLOOKUP(A289,FLEXPLP!A:A,1,0)),"N","Y") -> N | E289: =IF(ISERROR(VLOOKUP(A289,'ELN PLP'!A:A,1,0)),"N","Y") -> N | F289: =IF(COUNTIF(B289:E289,"Y")>0,1,0) -> 0 | G289: =IF(ISERROR(VLOOKUP(A289,RDPLP!D:D,1,0)),"N","Y") -> N | H289: =IF(ISERROR(VLOOKUP(A289,'SCINET-PLP'!D:D,1,0)),"N","Y") -> N | I289: =IF(ISERROR(VLOOKUP(A289,FLEXPLP!D:D,1,0)),"N","Y") -> N | J289: =IF(ISERROR(VLOOKUP(A289,'ELN PLP'!D:D,1,0)),"N","Y") -> N | K289: =IF(COUNTIF(G289:J289,"Y")>0,1,0) -> 0 | L289: =IF(ISERROR(VLOOKUP(A289,RDPLP!G:G,1,0)),"N","Y") -> N | M289: =IF(ISERROR(VLOOKUP(A289,'SCINET-PLP'!G:G,1,0)),"N","Y") -> N | N289: =IF(ISERROR(VLOOKUP(A289,FLEXPLP!G:G,1,0)),"N","Y") -> N | O289: =IF(ISERROR(VLOOKUP(A289,'ELN PLP'!G:G,1,0)),"N","Y") -> N | P289: =IF(COUNTIF(L289:O289,"Y")>0,1,0) -> 0 | R289: =IF(K289+F289>0,1,0) -> 0 | S289: =IF(ISERROR(VLOOKUP(A289,U:U,1,0)),0,1) -> 0
A290: Naseef.Khan | B290: =IF(ISERROR(VLOOKUP(A290,RDPLP!A290:A315,1,0)),"N","Y") -> N | C290: =IF(ISERROR(VLOOKUP(A290,'SCINET-PLP'!A:A,1,0)),"N","Y") -> N | D290: =IF(ISERROR(VLOOKUP(A290,FLEXPLP!A:A,1,0)),"N","Y") -> N | E290: =IF(ISERROR(VLOOKUP(A290,'ELN PLP'!A:A,1,0)),"N","Y") -> N | F290: =IF(COUNTIF(B290:E290,"Y")>0,1,0) -> 0 | G290: =IF(ISERROR(VLOOKUP(A290,RDPLP!D:D,1,0)),"N","Y") -> N | H290: =IF(ISERROR(VLOOKUP(A290,'SCINET-PLP'!D:D,1,0)),"N","Y") -> N | I290: =IF(ISERROR(VLOOKUP(A290,FLEXPLP!D:D,1,0)),"N","Y") -> N | J290: =IF(ISERROR(VLOOKUP(A290,'ELN PLP'!D:D,1,0)),"N","Y") -> N | K290: =IF(COUNTIF(G290:J290,"Y")>0,1,0) -> 0 | L290: =IF(ISERROR(VLOOKUP(A290,RDPLP!G:G,1,0)),"N","Y") -> N | M290: =IF(ISERROR(VLOOKUP(A290,'SCINET-PLP'!G:G,1,0)),"N","Y") -> N | N290: =IF(ISERROR(VLOOKUP(A290,FLEXPLP!G:G,1,0)),"N","Y") -> N | O290: =IF(ISERROR(VLOOKUP(A290,'ELN PLP'!G:G,1,0)),"N","Y") -> N | P290: =IF(COUNTIF(L290:O290,"Y")>0,1,0) -> 0 | R290: =IF(K290+F290>0,1,0) -> 0 | S290: =IF(ISERROR(VLOOKUP(A290,U:U,1,0)),0,1) -> 0
A291: Nicholas.Brownbill | B291: =IF(ISERROR(VLOOKUP(A291,RDPLP!A291:A316,1,0)),"N","Y") -> N | C291: =IF(ISERROR(VLOOKUP(A291,'SCINET-PLP'!A:A,1,0)),"N","Y") -> N | D291: =IF(ISERROR(VLOOKUP(A291,FLEXPLP!A:A,1,0)),"N","Y") -> N | E291: =IF(ISERROR(VLOOKUP(A291,'ELN PLP'!A:A,1,0)),"N","Y") -> N | F291: =IF(COUNTIF(B291:E291,"Y")>0,1,0) -> 0 | G291: =IF(ISERROR(VLOOKUP(A291,RDPLP!D:D,1,0)),"N","Y") -> N | H291: =IF(ISERROR(VLOOKUP(A291,'SCINET-PLP'!D:D,1,0)),"N","Y") -> N | I291: =IF(ISERROR(VLOOKUP(A291,FLEXPLP!D:D,1,0)),"N","Y") -> N | J291: =IF(ISERROR(VLOOKUP(A291,'ELN PLP'!D:D,1,0)),"N","Y") -> N | K291: =IF(COUNTIF(G291:J291,"Y")>0,1,0) -> 0 | L291: =IF(ISERROR(VLOOKUP(A291,RDPLP!G:G,1,0)),"N","Y") -> N | M291: =IF(ISERROR(VLOOKUP(A291,'SCINET-PLP'!G:G,1,0)),"N","Y") -> N | N291: =IF(ISERROR(VLOOKUP(A291,FLEXPLP!G:G,1,0)),"N","Y") -> N | O291: =IF(ISERROR(VLOOKUP(A291,'ELN PLP'!G:G,1,0)),"N","Y") -> N | P291: =IF(COUNTIF(L291:O291,"Y")>0,1,0) -> 0 | R291: =IF(K291+F291>0,1,0) -> 0 | S291: =IF(ISERROR(VLOOKUP(A291,U:U,1,0)),0,1) -> 0
... A361: zaida.salazar | B361: =IF(ISERROR(VLOOKUP(A361,RDPLP!A361:A386,1,0)),"N","Y") -> N | C361: =IF(ISERROR(VLOOKUP(A361,'SCINET-PLP'!A:A,1,0)),"N","Y") -> N | D361: =IF(ISERROR(VLOOKUP(A361,FLEXPLP!A:A,1,0)),"N","Y") -> N | E361: =IF(ISERROR(VLOOKUP(A361,'ELN PLP'!A:A,1,0)),"N","Y") -> N | F361: =IF(COUNTIF(B361:E361,"Y")>0,1,0) -> 0 | G361: =IF(ISERROR(VLOOKUP(A361,RDPLP!D:D,1,0)),"N","Y") -> N | H361: =IF(ISERROR(VLOOKUP(A361,'SCINET-PLP'!D:D,1,0)),"N","Y") -> N | I361: =IF(ISERROR(VLOOKUP(A361,FLEXPLP!D:D,1,0)),"N","Y") -> N | J361: =IF(ISERROR(VLOOKUP(A361,'ELN PLP'!D:D,1,0)),"N","Y") -> N | K361: =IF(COUNTIF(G361:J361,"Y")>0,1,0) -> 0 | L361: =IF(ISERROR(VLOOKUP(A361,RDPLP!G:G,1,0)),"N","Y") -> N | M361: =IF(ISERROR(VLOOKUP(A361,'SCINET-PLP'!G:G,1,0)),"N","Y") -> N | N361: =IF(ISERROR(VLOOKUP(A361,FLEXPLP!G:G,1,0)),"N","Y") -> N | O361: =IF(ISERROR(VLOOKUP(A361,'ELN PLP'!G:G,1,0)),"N","Y") -> N | P361: =IF(COUNTIF(L361:O361,"Y")>0,1,0) -> 0 | R361: =IF(K361+F361>0,1,0) -> 0 | S361: =IF(ISERROR(VLOOKUP(A361,U:U,1,0)),0,1) -> 0
A363: Total | B363: =COUNTIF(B3:B362,"Y") -> 26 | C363: =COUNTIF(C3:C362,"Y") -> 28 | D363: =COUNTIF(D3:D362,"Y") -> 23 | E363: =COUNTIF(E3:E362,"Y") -> 77 | F363: =SUM(F3:F361) -> 128 | G363: =COUNTIF(G3:G362,"Y") -> 30 | H363: =COUNTIF(H3:H362,"Y") -> 33 | I363: =COUNTIF(I3:I362,"Y") -> 22 | J363: =COUNTIF(J3:J362,"Y") -> 62 | K363: =SUM(K3:K361) -> 119 | L363: =COUNTIF(L3:L362,"Y") -> 30 | M363: =COUNTIF(M3:M362,"Y") -> 26 | N363: =COUNTIF(N3:N362,"Y") -> 25 | O363: =COUNTIF(O3:O362,"Y") -> 40 | P363: =SUM(P3:P361) -> 92 | R363: =SUM(R3:R361) -> 185 | S363: =SUM(S3:S361) -> 0
A365: Check | B365: 26 | C365: 28 | D365: 23 | E365: 77 | F365: 128 | G365: 30 | H365: 33 | I365: 22 | J365: 62 | K365: 119 | L365: 30 | M365: 26 | N365: 25 | O365: 40 | P365: 92 | R365: 185 | S365: 278

Sheet RDPLP
A1: January | D1: February | G1: March
A2: Username | B2: Usage/month | D2: Username | E2: Usage/month | G2: Username | H2: Usage/month
A3: amautomation.nonsap2 | B3: 22 | D3: bhakti.varadkar | E3: 1 | G3: catherine.stolton | H3: 6
A4: helena.johnston | B4: 3 | D4: palani.poojitha | E4: 7 | G4: samuel.sandiford | H4: 5
A5: kareena.bains | B5: 6 | D5: andrew.ng | E5: 7 | G5: naomi.petch | H5: 1
A6: emma.elliott | B6: 7 | D6: stephen.boothroyd | E6: 5 | G6: sona.mihokova | H6: 1
A7: andrew.ng | B7: 3 | D7: jamie.yip | E7: 1 | G7: paul.carpenter | H7: 1
A8: arun.khuntia | B8: 1 | D8: andrew.mitchell | E8: 2 | G8: kareena.bains | H8: 2
A9: adam.newbould | B9: 2 | D9: carlo.faggiotto | E9: 2 | G9: stephen.boothroyd | H9: 2
A10: noah.phipps | B10: 2 | D10: emma.lewis | E10: 1 | G10: matthew.tynan | H10: 1
A11: rahida.islam | B11: 1 | D11: amautomation.nonsap2 | E11: 20 | G11: andrew.ng | H11: 13
A12: andrew.a.barnes | B12: 5 | D12: svc_ems_api | E12: 6 | G12: katie.oake | H12: 1
A13: bhakti.varadkar | B13: 4 | D13: sarah.gilligan | E13: 6 | G13: emma.elliott | H13: 3
A14: samuel.sandiford | B14: 1 | D14: helena.johnston | E14: 2 | G14: andrew.a.barnes | H14: 11
... A28: katie.oake | B28: 2 | D28: noah.phipps | E28: 1 | G28: amautomation.nonsap2 | H28: 22
D29: katie.oake | E29: 1 | G29: gerta.kotsi | H29: 1
D30: harry.rostron | E30: 2 | G30: jamie.yip | H30: 1
D31: samuel.sandiford | E31: 1 | G31: carlo.faggiotto | H31: 9
D32: naomi.petch | E32: 1 | G32: arun.khuntia | H32: 3
G33: ashelyn.kyne | H33: 2
G34: elilan.yogenthiran2 | H34: 1
G35: helena.johnston | H35: 1
G36: andrew.p.parker | H36: 14

Sheet PO Details
A2: 2026 PO | B2: Reference Document | C2: Owner/User | D2: Director | E2: Description | F2: Start date | G2: End Date | H2: No of License | I2: Cost | J2: Currency | K2: License Key
A3: PO17269130 | B3: RN0001875285 | C3: Ian Stott | D3: Adam Kowalski | E3: PLP Prof | F3: 46023 | G3: 46387 | H3: 5 | I3: 10002 | J3: Euro | K3: 200000000048907_BIO_PP00000000397_0032_1
A4: PO17268090 | B4: RN0001875313 | C4: R Nurrish | D4: Jen Starkey | E4: 3DX - IWU | F4: 46023 | G4: 46387 | H4: 300 | I4: 35088.66 | J4: Euro | K4: 200000000048907_BIO_PP00000000397_0032_1
A5: PO17277421 | B5: RN0001713371 | C5: Naga, NG | D5: Jen Starkey | E5: ELN | F5: 46023 | G5: 46387 | H5: 1953 | I5: 502869 | J5: Euro | K5: UNILEVER U.K. CENTRAL RESOURCES LTD_1953_NBU_LKO4072427_Case#25004560
A6: PO17277423 | B6: RN0001710847 | C6: Ian Stott | D6: Adam Kowalski | E6: PLP $ | F6: 46023 | G6: 46387 | H6: 185 | I6: 219501 | J6: Euro | K6: 200000000048907_BIO_PP00000000397_0032_1
I7: =SUM(I3:I6) -> 767460.66 | J7: Euro

Sheet SCINET-PLP
A1: January | D1: February | G1: March
A2: Username | B2: Usage/month | D2: Username | E2: Usage/month | G2: Username | H2: Usage/month
A3: satyajit.samadder | B3: 25 | D3: rohit.mahale | E3: 15 | G3: satyajit.samadder | H3: 3
A4: rohit.mahale | B4: 11 | D4: inna.zalmanovich | E4: 1 | G4: rosemarie.derbyshire | H4: 1
A5: ram.rajagopal | B5: 1 | D5: anne-sophie.piggott | E5: 3 | G5: james.youlton | H5: 1
A6: anastasia.panteli | B6: 1 | D6: adam.mcdonald | E6: 3 | G6: parag.shah | H6: 1
A7: calum.thomas | B7: 1 | D7: deepakraj.yadav | E7: 3 | G7: c.priyanka | H7: 2
A8: jyoti.gupta | B8: 2 | D8: mark.carus | E8: 2 | G8: jeffery.liu | H8: 1
A9: anne-sophie.piggott | B9: 1 | D9: nandhini.j | E9: 3 | G9: marc.woolfall | H9: 2
A10: mark.carus | B10: 3 | D10: ieva.gripkauskaite | E10: 1 | G10: samuel.sandiford | H10: 2
A11: elizabeth.jamie | B11: 1 | D11: satyajit.samadder | E11: 27 | G11: thomas.fishwick | H11: 3
A12: adam.mcdonald | B12: 2 | D12: carole.pavan | E12: 1 | G12: mark.smith3 | H12: 2
A13: morena.tondini | B13: 1 | D13: jeffery.liu | E13: 1 | G13: simon.fraser | H13: 2
A14: koushik.a | B14: 1 | D14: alexandre.de-casson | E14: 3 | G14: sneha.manohar | H14: 1
... A30: nivedita.patil | B30: 4 | D30: vibha.s | E30: 7 | G30: tinto.alencherry | H30: 12
D31: vidyalakshmi.cm | E31: 19 | G31: ian.stott | H31: 4
D32: adrian.williams | E32: 7 | G32: manu.george | H32: 19
D33: calum.thomas | E33: 3 | G33: adrian.williams | H33: 8
D34: jyoti.gupta | E34: 5
D35: pintu.paul | E35: 7

Sheet FLEXPLP
A1: January | D1: February | G1: March
A2: Username | B2: Usage/month | D2: Username | E2: Usage/month | G2: Username | H2: Usage/month
A3: plp_access | B3: 22 | D3: palani.poojitha | E3: 2 | G3: andrew.ng | H3: 18
A4: andrew.a.barnes | B4: 6 | D4: andrew.a.barnes | E4: 8 | G4: noah.phipps | H4: 10
A5: harry.rostron | B5: 4 | D5: svc_plpdev | E5: 5 | G5: andrew.mitchell | H5: 5
A6: emma.elliott | B6: 7 | D6: helena.johnston | E6: 2 | G6: plp_access | H6: 27
A7: minna.tereva | B7: 2 | D7: katie.oake | E7: 1 | G7: emma.lewis | H7: 18
A8: adam.newbould | B8: 1 | D8: harry.rostron | E8: 1 | G8: emma.elliott | H8: 5
A9: katie.oake | B9: 2 | D9: samuel.sandiford | E9: 1 | G9: andrew.a.barnes | H9: 11
A10: kareena.bains | B10: 7 | D10: naomi.petch | E10: 1 | G10: sarah.gilligan | H10: 4
A11: robert.simpson | B11: 4 | D11: bhakti.varadkar | E11: 1 | G11: carlo.faggiotto | H11: 7
A12: samuel.sandiford | B12: 1 | D12: catherine.stolton | E12: 7 | G12: ashelyn.kyne | H12: 2
A13: arun.khuntia | B13: 1 | D13: kareena.bains | E13: 5 | G13: stephen.boothroyd | H13: 1
A14: catherine.stolton | B14: 2 | D14: emma.lewis | E14: 2 | G14: catherine.stolton | H14: 8
... A24: andrew.ng | B24: 9 | D24: rahida.islam | E24: 2 | G24: naomi.petch | H24: 1
A25: andrew.mitchell | B25: 3 | G25: sona.mihokova | H25: 2
G26: robert.simpson | H26: 6
G27: paul.carpenter | H27: 1
G28: elilan.yogenthiran2 | H28: 1

Sheet ELN PLP
A1: January | D1: February | G1: March
A2: Username | B2: Usage/month | D2: Username | E2: Usage/month | G2: Username | H2: Usage/month
A3: amautomation.nonsap2 | B3: 22 | D3: amautomation.nonsap2 | E3: 20 | G3: arun.khuntia | H3: 19
A4: sheena.payne | B4: 4 | D4: arnold-de.graaf | E4: 7 | G4: amautomation.nonsap2 | H4: 23
A5: catherine.stolton | B5: 1 | D5: patricia.heussen | E5: 4 | G5: deepti.chitnis | H5: 5
A6: sara.filgueira-marti | B6: 1 | D6: niels-de.roo | E6: 11 | G6: niels-de.roo | H6: 4
A7: tjerk.bouman | B7: 1 | D7: james.marshall | E7: 2 | G7: patricia.heussen | H7: 4
A8: hakan.cay | B8: 1 | D8: teresa.loughbrough | E8: 1 | G8: lisa.fildes | H8: 2
A9: gerard.volante | B9: 2 | D9: sheena.payne | E9: 4 | G9: patrick.paul | H9: 1
A10: sebastian.mjornstedt | B10: 2 | D10: khateejah.iqbal | E10: 2 | G10: kunal.pawar | H10: 1
A11: larissa.mortean | B11: 1 | D11: melissa.tiskaya | E11: 1 | G11: lauren.jones | H11: 1
A12: alois.popp | B12: 1 | D12: mandie.adams | E12: 3 | G12: luong-nh.thuy | H12: 1
A13: john.hubbard | B13: 1 | D13: kamile.garuolyte | E13: 1 | G13: lorena.galluzzi | H13: 2
A14: skylar.zhang | B14: 1 | D14: max.molendijk | E14: 1 | G14: william.lathrop | H14: 1
... A64: jason.williams | B64: 1 | D64: jyotirmayee.parida | E64: 10 | G64: marco.galli | H64: 1
A65: ozge.altun | B65: 1 | G65: nick.page | H65: 1
A66: sabrina.codazzi | B66: 1 | G66: carol.shek | H66: 1
A67: marc.woolfall | B67: 1 | G67: thomas.fell | H67: 1
A68: lonneke.zuidgeest | B68: 2
A69: andrew.rose | B69: 1
A70: samantha.roberts | B70: 1
A71: carol.shek | B71: 1
A72: pearl.onyeneke | B72: 2
A73: juliana.barany | B73: 1
A74: lisa.scott | B74: 1
A75: massimiliano.trentin | B75: 1
A76: liesbeth.bouwens | B76: 1
A77: mustapha-el.ouagmiri | B77: 1
A78: arun.khuntia | B78: 18
A79: jyotirmayee.parida | B79: 18
